trosnoth/__init__.py
trosnoth/aioreactor.py
trosnoth/botprocess.py
trosnoth/const.py
trosnoth/dbqueue.py
trosnoth/game.py
trosnoth/gpl.txt
trosnoth/keymap.py
trosnoth/main.py
trosnoth/manholehelper.py
trosnoth/music.py
trosnoth/settings.py
trosnoth/sound.py
trosnoth/themes.py
trosnoth/version.py
trosnoth/bots/__init__.py
trosnoth/bots/balance.py
trosnoth/bots/base.py
trosnoth/bots/goalsetter.py
trosnoth/bots/john.py
trosnoth/bots/onezone.py
trosnoth/bots/orders.py
trosnoth/bots/ordertest.py
trosnoth/bots/pathfinding.py
trosnoth/bots/pathtest.py
trosnoth/bots/puppet.py
trosnoth/bots/ranger.py
trosnoth/bots/silver.py
trosnoth/bots/sirrobin.py
trosnoth/bots/terminator.py
trosnoth/bots/test/__init__.py
trosnoth/data/__init__.py
trosnoth/data/edges.db
trosnoth/data/points.db
trosnoth/data/achievements/accuracyLarge.png
trosnoth/data/achievements/accuracyMedium.png
trosnoth/data/achievements/accuracySmall.png
trosnoth/data/achievements/aliveStreak.png
trosnoth/data/achievements/bulletsMedium.png
trosnoth/data/achievements/bulletsSmall.png
trosnoth/data/achievements/buyEveryUpgrade.png
trosnoth/data/achievements/darkZoneKills.png
trosnoth/data/achievements/default.png
trosnoth/data/achievements/destroyShield.png
trosnoth/data/achievements/developerKills.png
trosnoth/data/achievements/elephantSteal.png
trosnoth/data/achievements/firstKill.png
trosnoth/data/achievements/firstRespawn.png
trosnoth/data/achievements/firstTag.png
trosnoth/data/achievements/goodManners.png
trosnoth/data/achievements/grenadeMultikill.png
trosnoth/data/achievements/killAsRabbit.png
trosnoth/data/achievements/killEveryLeader.png
trosnoth/data/achievements/killRabbit.png
trosnoth/data/achievements/longRangeKill.png
trosnoth/data/achievements/minimapDisruption.png
trosnoth/data/achievements/multiTagLarge.png
trosnoth/data/achievements/multiTagMedium.png
trosnoth/data/achievements/multiTagSmall.png
trosnoth/data/achievements/multiUpgradesMedium.png
trosnoth/data/achievements/multiUpgradesSmall.png
trosnoth-1.23.0.dist-info/LICENSE
trosnoth-1.23.0.dist-info/METADATA
trosnoth-1.23.0.dist-info/WHEEL
trosnoth-1.23.0.dist-info/top_level.txt
trosnoth-1.23.0.dist-info/RECORD
