Metadata-Version: 2.2
Name: trosnoth
Version: 1.23.0
Summary: Trosnoth network platform game
Home-page: http://www.trosnoth.org/
Author: J.D. Bartlett et al
Author-email: josh@trosnoth.org
Classifier: Development Status :: 5 - Production/Stable
Classifier: Environment :: MacOS X
Classifier: Environment :: Win32 (MS Windows)
Classifier: Environment :: X11 Applications
Classifier: Framework :: Twisted
Classifier: Intended Audience :: End Users/Desktop
Classifier: License :: OSI Approved :: GNU General Public License (GPL)
Classifier: Natural Language :: English
Classifier: Operating System :: OS Independent
Classifier: Programming Language :: Python
Classifier: Programming Language :: Python :: 3
Classifier: Programming Language :: Python :: 3.5
Classifier: Programming Language :: Python :: 3.6
Classifier: Topic :: Games/Entertainment :: Arcade
Classifier: Topic :: Games/Entertainment :: Side-Scrolling/Arcade Games
License-File: LICENSE
Requires-Dist: asgiref
Requires-Dist: pygame>=2.0.0
Requires-Dist: twisted>=15.0
Requires-Dist: simplejson
Requires-Dist: msgpack
Requires-Dist: PySide6
Requires-Dist: cryptography
Requires-Dist: pyOpenSSL
Dynamic: author
Dynamic: author-email
Dynamic: classifier
Dynamic: description
Dynamic: home-page
Dynamic: requires-dist
Dynamic: summary
